[
  {
    "manufacturer": "Huawei",
    "model": "SUN2000-3KTL-L1",
    "type": "hybrid",
    "ratedPowerKw": 3.0,
    "maxDCPowerKw": 4.5,
    "efficiency": 0.982,
    "mpptCount": 2,
    "mpptVoltageMin": 140,
    "mpptVoltageMax": 600,
    "maxInputVoltage": 600,
    "maxInputCurrent": 12.5,
    "outputVoltage": 220,
    "outputPhases": 1,
    "hasBatteryPort": true,
    "weight": 10.5,
    "warranty": 10,
    "costCOP": 4200000
  },
  {
    "manufacturer": "Huawei",
    "model": "SUN2000-5KTL-L1",
    "type": "hybrid",
    "ratedPowerKw": 5.0,
    "maxDCPowerKw": 7.5,
    "efficiency": 0.984,
    "mpptCount": 2,
    "mpptVoltageMin": 140,
    "mpptVoltageMax": 600,
    "maxInputVoltage": 600,
    "maxInputCurrent": 12.5,
    "outputVoltage": 220,
    "outputPhases": 1,
    "hasBatteryPort": true,
    "weight": 11.5,
    "warranty": 10,
    "costCOP": 5800000
  },
  {
    "manufacturer": "Huawei",
    "model": "SUN2000-10KTL-M1",
    "type": "string",
    "ratedPowerKw": 10.0,
    "maxDCPowerKw": 15.0,
    "efficiency": 0.985,
    "mpptCount": 2,
    "mpptVoltageMin": 200,
    "mpptVoltageMax": 800,
    "maxInputVoltage": 1100,
    "maxInputCurrent": 22.0,
    "outputVoltage": 380,
    "outputPhases": 3,
    "hasBatteryPort": false,
    "weight": 13.2,
    "warranty": 10,
    "costCOP": 8500000
  },
  {
    "manufacturer": "SMA",
    "model": "Sunny Boy 3.0",
    "type": "string",
    "ratedPowerKw": 3.0,
    "maxDCPowerKw": 5.4,
    "efficiency": 0.970,
    "mpptCount": 2,
    "mpptVoltageMin": 80,
    "mpptVoltageMax": 600,
    "maxInputVoltage": 600,
    "maxInputCurrent": 10.0,
    "outputVoltage": 220,
    "outputPhases": 1,
    "hasBatteryPort": false,
    "weight": 9.2,
    "warranty": 10,
    "costCOP": 3900000
  },
  {
    "manufacturer": "SMA",
    "model": "Sunny Boy 5.0",
    "type": "string",
    "ratedPowerKw": 5.0,
    "maxDCPowerKw": 7.5,
    "efficiency": 0.972,
    "mpptCount": 2,
    "mpptVoltageMin": 80,
    "mpptVoltageMax": 600,
    "maxInputVoltage": 600,
    "maxInputCurrent": 12.0,
    "outputVoltage": 220,
    "outputPhases": 1,
    "hasBatteryPort": false,
    "weight": 9.5,
    "warranty": 10,
    "costCOP": 5200000
  },
  {
    "manufacturer": "SMA",
    "model": "Sunny Tripower 10.0",
    "type": "string",
    "ratedPowerKw": 10.0,
    "maxDCPowerKw": 15.0,
    "efficiency": 0.980,
    "mpptCount": 2,
    "mpptVoltageMin": 150,
    "mpptVoltageMax": 800,
    "maxInputVoltage": 1000,
    "maxInputCurrent": 18.0,
    "outputVoltage": 380,
    "outputPhases": 3,
    "hasBatteryPort": false,
    "weight": 25.0,
    "warranty": 10,
    "costCOP": 9200000
  },
  {
    "manufacturer": "Fronius",
    "model": "Primo 3.0-1",
    "type": "string",
    "ratedPowerKw": 3.0,
    "maxDCPowerKw": 4.5,
    "efficiency": 0.976,
    "mpptCount": 2,
    "mpptVoltageMin": 80,
    "mpptVoltageMax": 600,
    "maxInputVoltage": 600,
    "maxInputCurrent": 12.0,
    "outputVoltage": 220,
    "outputPhases": 1,
    "hasBatteryPort": false,
    "weight": 16.0,
    "warranty": 10,
    "costCOP": 4500000
  },
  {
    "manufacturer": "Fronius",
    "model": "Symo GEN24 5.0 Plus",
    "type": "hybrid",
    "ratedPowerKw": 5.0,
    "maxDCPowerKw": 7.5,
    "efficiency": 0.978,
    "mpptCount": 2,
    "mpptVoltageMin": 80,
    "mpptVoltageMax": 600,
    "maxInputVoltage": 600,
    "maxInputCurrent": 16.0,
    "outputVoltage": 220,
    "outputPhases": 1,
    "hasBatteryPort": true,
    "weight": 19.9,
    "warranty": 10,
    "costCOP": 7200000
  },
  {
    "manufacturer": "Growatt",
    "model": "MIN 3000TL-X",
    "type": "string",
    "ratedPowerKw": 3.0,
    "maxDCPowerKw": 4.5,
    "efficiency": 0.972,
    "mpptCount": 1,
    "mpptVoltageMin": 80,
    "mpptVoltageMax": 500,
    "maxInputVoltage": 550,
    "maxInputCurrent": 12.5,
    "outputVoltage": 220,
    "outputPhases": 1,
    "hasBatteryPort": false,
    "weight": 7.8,
    "warranty": 10,
    "costCOP": 2800000
  },
  {
    "manufacturer": "Growatt",
    "model": "SPH 5000TL BL-UP",
    "type": "hybrid",
    "ratedPowerKw": 5.0,
    "maxDCPowerKw": 7.5,
    "efficiency": 0.975,
    "mpptCount": 2,
    "mpptVoltageMin": 100,
    "mpptVoltageMax": 550,
    "maxInputVoltage": 600,
    "maxInputCurrent": 13.0,
    "outputVoltage": 220,
    "outputPhases": 1,
    "hasBatteryPort": true,
    "weight": 24.5,
    "warranty": 10,
    "costCOP": 5500000
  },
  {
    "manufacturer": "GoodWe",
    "model": "GW5000-NS",
    "type": "string",
    "ratedPowerKw": 5.0,
    "maxDCPowerKw": 6.5,
    "efficiency": 0.976,
    "mpptCount": 2,
    "mpptVoltageMin": 80,
    "mpptVoltageMax": 580,
    "maxInputVoltage": 600,
    "maxInputCurrent": 13.5,
    "outputVoltage": 220,
    "outputPhases": 1,
    "hasBatteryPort": false,
    "weight": 15.5,
    "warranty": 10,
    "costCOP": 4100000
  }
]
